[{
        "name": "bangus (milkfish)"
    },
    {
        "name": "glutinous rice"
    },
    {
        "name": "kalamansi"
    },
    {
        "name": "kangkong (water spinach)"
    },
    {
        "name": "winter melon"
    },
    {
        "name": "white radish"
    },
    {
        "name": "mung bean"
    },
    {
        "name": "spam"
    },
    {
        "name": "banana heart"
    },
    {
        "name": "taiwanese cabbage"
    },
    {
        "name": "chayote"
    },
    {
        "name": "sitaw (yardlong bean)"
    },
    {
        "name": "parmesan cheese"
    },
    {
        "name": "ube"
    },
    {
        "name": "ube extract"
    },
    {
        "name": "agar"
    },
    {
        "name": "pandan"
    },
    {
        "name": "pandan extract"
    },
    {
        "name": "banana ketchup"
    },
    {
        "name": "liver pâté"
    },
    {
        "name": "coconut vinegar"
    },
    {
        "name": "toyomansi (kalamansi soy sauce)"
    },
    {
        "name": "tajin"
    },
    {
        "name": "berbere"
    },
    {
        "name": "mitmita"
    },
    {
        "name": "shiro powder"
    },
    {
        "name": "enjera"
    },
    {
        "name": "tamarind"
    },
    {
        "name": "dried ancho chilies"
    },
    {
        "name": "chile quebrado (crushed)"
    },
    {
        "name": "achiote rojo"
    },
    {
        "name": "achiote verde"
    },
    {
        "name": "queso panela"
    },
    {
        "name": "maseca corn flour"
    },
    {
        "name": "sumac"
    },
    {
        "name": "date molasses"
    },
    {
        "name": "whole cloves"
    },
    {
        "name": "za'atar"
    },
    {
        "name": "rose water"
    },
    {
        "name": "nigella seeds"
    },
    {
        "name": "gochugaru (korean chili powder)"
    },
    {
        "name": "roasted sesame seeds"
    },
    {
        "name": "shaoxing wine"
    },
    {
        "name": "anchovy fish sauce"
    },
    {
        "name": "perilla oil"
    },
    {
        "name": "gochujang (korean chili paste)"
    },
    {
        "name": "doenjang (soybean paste)"
    },
    {
        "name": "ssamjang (korean spicy dipping sauce)"
    },
    {
        "name": "chunjang (korean black bean paste sauce)"
    },
    {
        "name": "sushi rice"
    },
    {
        "name": "dangmyeon (sweet potato noodles)"
    },
    {
        "name": "perilla leaves"
    },
    {
        "name": "kombu"
    },
    {
        "name": "miyeok (sea mustard)"
    },
    {
        "name": "katsuobushi (dried bonito flakes)"
    },
    {
        "name": "dried anchovy"
    },
    {
        "name": "nori (unseasoned seaweed)"
    },
    {
        "name": "kizame nori (shredded nori)"
    },
    {
        "name": "ajitsuke nori (seasoned nori)"
    },
    {
        "name": "seasoned seaweed"
    },
    {
        "name": "korean fish cakes"
    },
    {
        "name": "sake "
    },
    {
        "name": "soju"
    },
    {
        "name": "dashi"
    },
    {
        "name": "aka miso (red miso)"
    },
    {
        "name": "shiro miso (white miso)"
    },
    {
        "name": "awase miso (yellow miso)"
    },
    {
        "name": "koji miso"
    },
    {
        "name": "mugi miso (barley miso)"
    },
    {
        "name": "mame miso (soybean miso)"
    },
    {
        "name": "rice miso (kome miso)"
    },
    {
        "name": "black vinegar"
    },
    {
        "name": "instant dashi"
    },
    {
        "name": "awamori"
    },
    {
        "name": "dried shiitake mushroom"
    },
    {
        "name": "fukujinzuke (pickled daikon)"
    },
    {
        "name": "dried wood ear mushroom"
    },
    {
        "name": "matcha powder"
    },
    {
        "name": "chikuwa (japanese fish cake)"
    },
    {
        "name": "ikura (salmon roe)"
    },
    {
        "name": "imitation crab sticks"
    },
    {
        "name": "inariage (seasoned fried tofu pouch)"
    },
    {
        "name": "harusame (glass noodles)"
    },
    {
        "name": "enoki mushroom"
    },
    {
        "name": "gobo (burdock root)"
    },
    {
        "name": "ume (green plum)"
    },
    {
        "name": "kinako"
    },
    {
        "name": "mochiko (sweet rice flour)"
    },
    {
        "name": "mochi"
    },
    {
        "name": "kirimochi"
    },
    {
        "name": "anko (red bean paste)"
    },
    {
        "name": "azuki beans"
    },
    {
        "name": "black soybeans"
    },
    {
        "name": "gingko nuts"
    },
    {
        "name": "natto"
    },
    {
        "name": "dried chili peppers"
    },
    {
        "name": "red szechuan peppercorn"
    },
    {
        "name": "green szechuan peppercorn"
    },
    {
        "name": "doubanjiang (fermented spicy bean paste)"
    },
    {
        "name": "dark soy sauce"
    },
    {
        "name": "toasted sesame oil"
    },
    {
        "name": "dried lily flowers"
    },
    {
        "name": "deep fried tofu"
    },
    {
        "name": "dried shrimp"
    },
    {
        "name": "fermented bean curd"
    },
    {
        "name": "fermented black beans"
    },
    {
        "name": "saujeot (salted fermented shrimp)"
    },
    {
        "name": "kha (galangal)"
    },
    {
        "name": "bird eye chilies"
    },
    {
        "name": "thai shrimp paste"
    },
    {
        "name": "fresh shallot"
    },
    {
        "name": "fried shallots"
    },
    {
        "name": "boba pearls"
    },
    {
        "name": "sago pearls"
    },
    {
        "name": "taro"
    },
    {
        "name": "tapioca starch"
    }
]